rhalphalib/__init__.py
rhalphalib/function.py
rhalphalib/model.py
rhalphalib/parameter.py
rhalphalib/sample.py
rhalphalib/template_morph.py
rhalphalib/util.py
rhalphalib/version.py
rhalphalib/plot/__init__.py
rhalphalib/plot/input_shapes.py
rhalphalib/plot/plot_TF.py
rhalphalib/plot/plot_cov.py
rhalphalib-0.3.0.dist-info/LICENSE
rhalphalib-0.3.0.dist-info/METADATA
rhalphalib-0.3.0.dist-info/WHEEL
rhalphalib-0.3.0.dist-info/top_level.txt
rhalphalib-0.3.0.dist-info/RECORD
