Metadata-Version: 2.2
Name: rhalphalib
Version: 0.3.0
Summary: A binned fit intermediate representation library
Author-email: Nick Smith <nick.smith@cern.ch>
Maintainer-email: Nick Smith <nick.smith@cern.ch>
License: BSD-3-Clause
Project-URL: Homepage, https://github.com/nsmith-/rhalphalib
Classifier: Development Status :: 4 - Beta
Classifier: Intended Audience :: Science/Research
Classifier: License :: OSI Approved :: BSD License
Classifier: Programming Language :: Python
Classifier: Programming Language :: Python :: 3
Classifier: Topic :: Scientific/Engineering :: Physics
Requires-Python: >=3.8
License-File: LICENSE
Requires-Dist: numpy>=1.14
Requires-Dist: scipy
Requires-Dist: mplhep
Provides-Extra: test
Requires-Dist: pytest; extra == "test"
Provides-Extra: dev
Requires-Dist: pre-commit; extra == "dev"
Provides-Extra: docs
Requires-Dist: sphinx>=7.0; extra == "docs"
Requires-Dist: myst_parser>=0.13; extra == "docs"
Requires-Dist: sphinx_copybutton; extra == "docs"
Requires-Dist: sphinx_autodoc_typehints; extra == "docs"
Requires-Dist: furo>=2023.08.17; extra == "docs"
